{"content": [["xander schauffele", "none", "none", {"$oid": "64d8ea77516b2658721149e4"}, "Left", "2021-08-01 05:37:58", "rappler.com", 73047], ["xander schauffele", "rattijuoppo", "stefan schauffele", {"$oid": "64d8ea77516b265872114aad"}, "Left", "2021-08-01 07:10:00", "hs", 40366], ["xander schauffele", "none", "none", {"$oid": "64d8eed2516b2658729fe3b5"}, "CenterRight", "2021-08-01 03:14:58", "National Post", 300411], ["xander schauffele", "hideki matsuyama", "none", {"$oid": "64d8ea77516b265872114b0e"}, "Left", "2021-08-01 08:41:00", "kunm.org", 146446], ["xander schauffele", "none", "none", {"$oid": "64d8ebc6516b2658723b9187"}, "CenterLeft", "2021-08-01 03:15:31", "Independent", 41150], ["xi jinping", "none", "none", {"$oid": "64d8f13d516b265872efbd02"}, "Left", "2021-07-01 05:29:29", "thisisinsider.com", 287512], ["xi jinping", "mao zedong", "chinese people", {"$oid": "64d8f13d516b265872efba82"}, "Left", "2021-07-01 01:20:20", "ELIMPARCIAL.COM - Noticias, Clasificados e Informaci\u00f3n de Hermosillo, Sonora, M\u00e9xico.", 239478], ["xi jinping", "foreign force", "none", {"$oid": "64d8f13d516b265872efbb53"}, "Left", "2021-07-01 02:57:58", "newsclick.in", 105253], ["xi jinping", "united states", "north korea", {"$oid": "64d8eb34516b2658722866fa"}, "CenterLeft", "2021-07-01 00:07:40", "Seattle Times", 24940], ["xavier becerra", "none", "none", {"$oid": "64d8f1b7516b265872005a86"}, "Right", "2021-07-01 06:34:36", "drrichswier.com", 130197], ["xi jinping", "foreign forces", "taiwan", {"$oid": "64d8f1b7516b265872005827"}, "Right", "2021-07-01 02:24:55", "Document.no", 365809], ["xi jinping", "foreign countries", "china", {"$oid": "64d8f1b0516b265872ff4e84"}, "CenterRight", "2021-07-01 00:15:14", "kvia.com", 95251], ["xi jinping", "foreign countries", "none", {"$oid": "64d8f1b0516b265872ff4e43"}, "CenterRight", "2021-07-01 00:15:14", "localnews8.com", 22905], ["xi jinping", "none", "none", {"$oid": "64d8f1b0516b265872ff4f18"}, "CenterRight", "2021-07-01 00:37:18", "localnews8.com", 22905], ["xi jinping", "none", "none", {"$oid": "64d8f1b0516b265872ff4f5b"}, "CenterRight", "2021-07-01 00:37:18", "kvia.com", 95251], ["xi jinping", "foreign forces attempting to bully china", "none", {"$oid": "64d8f1b0516b265872ff4e3a"}, "CenterRight", "2021-07-01 00:13:06", "financialpost.com", 22886], ["xavier guille des buttes", "none", "none", {"$oid": "64d8ee1f516b26587289499a"}, "Center", "2021-07-15 00:00:00", "cn.linkedin.com", 57174], ["xi jinping", "chinese communist party", "hong kong citizens", {"$oid": "64d8ee1f516b265872894ad4"}, "Center", "2021-07-01 00:02:24", "geo-tv", 41437], ["xi jinping", "foreign force", "chinese people", {"$oid": "64d8ee1f516b265872894d6d"}, "Center", "2021-07-01 00:49:14.941007", "newindianexpress.com", 100063], ["xavien howard", "miami dolphins", "bud light", {"$oid": "64d8f0fc516b265872e76f86"}, "FarLeft", "2021-07-27 21:53:00", "Upworthy", 26357], ["xavier campbell", "none", "none", {"$oid": "64d8eece516b2658729f5ba3"}, "CenterLeft", "2021-06-01 02:14:54", "watoday.com.au", 76958], ["xinjiang daqo new energy", "none", "none", {"$oid": "64d8eedc516b265872a12657"}, "Center", "2021-06-01 01:00:00", "PR Newswire", 19673], ["xtream1101", "none", "none", {"$oid": "64d8e9a6516b265872f68401"}, "CenterRight", "2021-05-01 00:54:43", "archive.org", 19233], ["xtream1101", "none", "none", {"$oid": "64d8e9a6516b265872f684bc"}, "CenterRight", "2021-05-01 01:24:39", "archive.org", 19233], ["xtream1101", "none", "none", {"$oid": "64d8e9a6516b265872f68544"}, "CenterRight", "2021-05-01 01:53:55", "archive.org", 19233], ["xtream1101", "none", "none", {"$oid": "64d8e9a6516b265872f68328"}, "CenterRight", "2021-05-01 00:22:43", "archive.org", 19233], ["xtream1101", "none", "none", {"$oid": "64d8e9a6516b265872f683f2"}, "CenterRight", "2021-05-01 00:54:11", "archive.org", 19233], ["xtream1101", "none", "none", {"$oid": "64d8e9a6516b265872f6854e"}, "CenterRight", "2021-05-01 01:54:13", "archive.org", 19233], ["xtream1101", "none", "none", {"$oid": "64d8e9a6516b265872f6856b"}, "CenterRight", "2021-05-01 01:54:42", "archive.org", 19233], ["xtream1101", "none", "none", {"$oid": "64d8e9a6516b265872f68555"}, "CenterRight", "2021-05-01 01:54:16", "archive.org", 19233], ["xtream1101", "none", "none", {"$oid": "64d8e9a6516b265872f68578"}, "CenterRight", "2021-05-01 01:55:01", "archive.org", 19233], ["xtream1101", "none", "none", {"$oid": "64d8e9a6516b265872f684a2"}, "CenterRight", "2021-05-01 01:24:23", "archive.org", 19233], ["xtream1101", "none", "none", {"$oid": "64d8e9a6516b265872f68575"}, "CenterRight", "2021-05-01 01:55:01", "archive.org", 19233], ["xtream1101", "none", "none", {"$oid": "64d8e9a6516b265872f6834e"}, "CenterRight", "2021-05-01 00:23:15", "archive.org", 19233], ["xtream1101", "vader", "libraries", {"$oid": "64d8e9a6516b265872f683e9"}, "CenterRight", "2021-05-01 00:53:48", "archive.org", 19233], ["xtream1101", "none", "none", {"$oid": "64d8e9a6516b265872f68560"}, "CenterRight", "2021-05-01 01:54:29", "archive.org", 19233], ["xtream1101", "none", "none", {"$oid": "64d8e9a6516b265872f68559"}, "CenterRight", "2021-05-01 01:54:17", "archive.org", 19233], ["xtream1101", "none", "none", {"$oid": "64d8e9a6516b265872f68498"}, "CenterRight", "2021-05-01 01:24:16", "archive.org", 19233], ["xtream1101", "none", "none", {"$oid": "64d8e9a6516b265872f68326"}, "CenterRight", "2021-05-01 00:22:42", "archive.org", 19233], ["xtream1101", "none", "none", {"$oid": "64d8e9a6516b265872f68495"}, "CenterRight", "2021-05-01 01:24:09", "archive.org", 19233], ["xtream1101", "none", "none", {"$oid": "64d8e9a6516b265872f6840b"}, "CenterRight", "2021-05-01 00:55:26", "archive.org", 19233], ["xtream1101", "none", "none", {"$oid": "64d8e9a6516b265872f68476"}, "CenterRight", "2021-05-01 01:23:59", "archive.org", 19233], ["xtream1101", "none", "none", {"$oid": "64d8e9a6516b265872f684d3"}, "CenterRight", "2021-05-01 01:24:56", "archive.org", 19233], ["xtream1101", "none", "none", {"$oid": "64d8e9a6516b265872f6855a"}, "CenterRight", "2021-05-01 01:54:27", "archive.org", 19233], ["xtream1101", "none", "none", {"$oid": "64d8e9a6516b265872f68572"}, "CenterRight", "2021-05-01 01:54:59", "archive.org", 19233], ["xtream1101", "none", "none", {"$oid": "64d8e9a6516b265872f6857d"}, "CenterRight", "2021-05-01 01:55:14", "archive.org", 19233], ["xtream1101", "m10", "libraries", {"$oid": "64d8e9a6516b265872f68481"}, "CenterRight", "2021-05-01 01:24:04", "archive.org", 19233], ["xtream1101", "none", "none", {"$oid": "64d8e9a6516b265872f684a5"}, "CenterRight", "2021-05-01 01:24:24", "archive.org", 19233], ["xtream1101", "none", "none", {"$oid": "64d8e9a6516b265872f68347"}, "CenterRight", "2021-05-01 00:23:11", "archive.org", 19233], ["xtream1101", "none", "none", {"$oid": "64d8e9a6516b265872f683cf"}, "CenterRight", "2021-05-01 00:53:36", "archive.org", 19233], ["xtream1101", "none", "none", {"$oid": "64d8e9a6516b265872f6840c"}, "CenterRight", "2021-05-01 00:55:27", "archive.org", 19233], ["xylor jane", "none", "none", {"$oid": "64d8ed28516b26587269c240"}, "Left", "2021-05-01 00:00:00", "artforum.com", 185385], ["xtream1101", "none", "none", {"$oid": "64d8f221516b2658720e51e3"}, "CenterRight", "2021-04-01 00:19:57", "archive.org", 19233], ["xtream1101", "villain", "libraries", {"$oid": "64d8f221516b2658720e52db"}, "CenterRight", "2021-04-01 00:51:22", "archive.org", 19233], ["xtream1101", "none", "none", {"$oid": "64d8f221516b2658720e53b3"}, "CenterRight", "2021-04-01 01:21:46", "archive.org", 19233], ["xtream1101", "none", "none", {"$oid": "64d8f221516b2658720e5373"}, "CenterRight", "2021-04-01 01:21:01", "archive.org", 19233], ["xtream1101", "none", "none", {"$oid": "64d8f221516b2658720e537a"}, "CenterRight", "2021-04-01 01:21:05", "archive.org", 19233], ["xtream1101", "none", "none", {"$oid": "64d8f221516b2658720e51bb"}, "CenterRight", "2021-04-01 00:19:56", "archive.org", 19233], ["xtream1101", "none", "none", {"$oid": "64d8f221516b2658720e523d"}, "CenterRight", "2021-04-01 00:20:32", "archive.org", 19233], ["xtream1101", "none", "libraries", {"$oid": "64d8f221516b2658720e5333"}, "CenterRight", "2021-04-01 01:20:49", "archive.org", 19233], ["xtream1101", "none", "palisade marker", {"$oid": "64d8f221516b2658720e53b6"}, "CenterRight", "2021-04-01 00:21:04", "archive.org", 19233], ["xtream1101", "none", "none", {"$oid": "64d8f221516b2658720e51ad"}, "CenterRight", "2021-04-01 00:19:47", "archive.org", 19233], ["xtream1101", "none", "libraries", {"$oid": "64d8f221516b2658720e5238"}, "CenterRight", "2021-04-01 00:20:23", "archive.org", 19233], ["xtream1101", "none", "none", {"$oid": "64d8f221516b2658720e5396"}, "CenterRight", "2021-04-01 01:21:22", "archive.org", 19233], ["xtream1101", "none", "libraries", {"$oid": "64d8f221516b2658720e53e3"}, "CenterRight", "2021-04-01 01:51:00", "archive.org", 19233], ["xtream1101", "none", "none", {"$oid": "64d8f221516b2658720e5478"}, "CenterRight", "2021-04-01 01:51:48", "archive.org", 19233], ["xtream1101", "none", "none", {"$oid": "64d8f221516b2658720e5469"}, "CenterRight", "2021-04-01 01:51:33", "archive.org", 19233], ["xtream1101", "none", "none", {"$oid": "64d8f221516b2658720e52d6"}, "CenterRight", "2021-04-01 00:20:52", "archive.org", 19233], ["xtream1101", "none", "none", {"$oid": "64d8f221516b2658720e5487"}, "CenterRight", "2021-04-01 01:52:06", "archive.org", 19233], ["xavier leclair", "none", "none", {"$oid": "64d8ec5c516b2658724eda74"}, "CenterLeft", "2021-04-01 02:22:43", "Independent", 41150], ["xtream1101", "vulture (3793667)", "libraries", {"$oid": "64d8f0d8516b265872e2af6b"}, "CenterRight", "2021-03-18 17:51:57", "archive.org", 19233], ["xtream1101", "none", "none", {"$oid": "64d8f0d4516b265872e228fe"}, "CenterRight", "2021-03-16 22:55:36", "archive.org", 19233], ["xtream1101", "none", "none", {"$oid": "64d8f0d9516b265872e2ce5a"}, "CenterRight", "2021-03-19 06:29:31", "archive.org", 19233], ["xtream1101", "none", "none", {"$oid": "64d8f0dd516b265872e35db7"}, "CenterRight", "2021-03-22 03:27:53", "archive.org", 19233], ["xtream1101", "none", "none", {"$oid": "64d8f0dd516b265872e3635d"}, "CenterRight", "2021-03-22 06:09:20", "archive.org", 19233], ["xtream1101", "none", "none", {"$oid": "64d8f0d7516b265872e286df"}, "CenterRight", "2021-03-18 07:08:37", "archive.org", 19233], ["xtream1101", "none", "none", {"$oid": "64d8f0db516b265872e32259"}, "CenterRight", "2021-03-20 16:13:42", "archive.org", 19233], ["xtream1101", "none", "none", {"$oid": "64d8f0d7516b265872e29828"}, "CenterRight", "2021-03-18 11:39:50", "archive.org", 19233], ["xtream1101", "none", "none", {"$oid": "64d8f0d6516b265872e27279"}, "CenterRight", "2021-03-17 22:04:08", "archive.org", 19233], ["xtream1101", "none", "none", {"$oid": "64d8f0d6516b265872e2608b"}, "CenterRight", "2021-03-17 16:02:00", "archive.org", 19233], ["xtream1101", "none", "none", {"$oid": "64d8f0dc516b265872e33ac9"}, "CenterRight", "2021-03-21 08:20:55", "archive.org", 19233], ["xpn", "none", "none", {"$oid": "64d8ea54516b2658720cb9ea"}, "Left", "2021-01-01 05:00:00", "boisestatepublicradio.org", 138019], ["xiaomi", "none", "none", {"$oid": "64d8ef0b516b265872a6e479"}, "Center", "2021-01-01 00:24:37", "Business Today", 283382], ["xiong liansheng", "china", "wuhan residents", {"$oid": "64d8f1c6516b265872023e37"}, "FarRight", "2021-01-11 04:33:41", "drudgereport", 1145], ["xiaomi", "huawei", "apple", {"$oid": "64d8ef67516b265872b32574"}, "CenterRight", "2020-12-01 00:45:44", "techradar.com", 22116], ["xavier becerra", "donald trump", "public health", {"$oid": "64d8e991516b265872f3c3f9"}, "FarLeft", "2020-12-14 10:00:01", "Salon", 1757], ["xavier p. loinaz", "none", "none", {"$oid": "64d8ea2c516b26587207af4f"}, "Left", "2020-11-01 04:48:07", "Manila Bulletin", 300382], ["xavi", "none", "none", {"$oid": "64d8e992516b265872f3e0f3"}, "FarLeft", "2020-12-21 15:15:31", "Upworthy", 26357], ["xi jinping", "unnamed mining company", "unnamed environmental group", {"$oid": "64d8ed28516b26587269c90a"}, "Center", "2020-11-01 01:00:00", "elcomercio-EC", 41029], ["xbox game pass ultimate", "none", "none", {"$oid": "64d8e993516b265872f40900"}, "CenterLeft", "2020-11-09 16:08:00", "screenrant.com", 69356], ["xavier becerra", "none", "alex padilla", {"$oid": "64d8ebf1516b265872412724"}, "FarLeft", "2020-11-10 17:10:44", "Taegan Goddard's Political Wire", 140], ["xavier becerra", "none", "none", {"$oid": "64d8ec5c516b2658724ec93c"}, "CenterRight", "2020-10-21 21:27:44", "hhs.gov", 19644], ["xi jinping", "none", "none", {"$oid": "64d8ee30516b2658728b6f9a"}, "Left", "2020-10-13 16:51:37", "chinadialogue.net", 33519], ["xi jinping", "none", "none", {"$oid": "64d8ed95516b26587278141c"}, "Center", "2020-10-21 00:00:00", "Xinhua China News Agency", 1711], ["xi jinping", "india", "nepal", {"$oid": "64d8edf7516b265872843ce3"}, "CenterRight", "2020-08-01 01:45:53", "HindustanTimes", 39872], ["xi jinping", "li wenliang", "li wenliang", {"$oid": "64d8ea77516b2658721144a0"}, "CenterLeft", "2020-07-15 00:00:00", "NBC News", 25499], ["ximena ibarra", "no villain identified", "none", {"$oid": "64d8ea26516b26587206fb96"}, "FarLeft", "2020-07-19 12:39:00", "Jacobin", 26811], ["xavier becerra", "donald trump", "sierra club v. trump", {"$oid": "64d8ef16516b265872a84333"}, "Left", "2020-06-27 09:30:01", "Salon", 1757], ["x rocker", "none", "none", {"$oid": "64d8ef13516b265872a7de8e"}, "Left", "2020-06-21 10:30:25", "Bustle", 98755], ["xiamen xiangyu", "china", "australian beef farmers", {"$oid": "64d8ec64516b265872500b21"}, "FarRight", "2020-06-21 21:13:06", "drudgereport", 1145], ["xi jinping", "none", "none", {"$oid": "64d8f0ac516b265872dcf291"}, "CenterLeft", "2020-05-15 00:00:00", "NBC News", 25499], ["xi jinping", "kim jong un", "united states", {"$oid": "64d8efc4516b265872beaf31"}, "CenterRight", null, "Wall Street Journal", 1150], ["xiong fei", "sars-cov-2", "bainianfeng catering management co.", {"$oid": "64d8ed2a516b2658726a128a"}, "FarRight", "2020-04-23 13:17:11", "Western Journalism Center", 6338], ["xavier equihua", "none", "none", {"$oid": "64d8f0a7516b265872dc3efa"}, "Center", null, "PR Newswire", 19673], ["xander", "none", "none", {"$oid": "64d8f1f1516b26587208000d"}, "CenterRight", "2019-05-01 11:00:00", "blogtalkradio.com", 20403], ["xavier castaneda", "none", "none", {"$oid": "64d8f084516b265872d7b8d6"}, "CenterRight", "2022-12-20 04:36:59", "krdo.com", 66979], ["xi jinping", "communist party", "chinese people", {"$oid": "64d8f064516b265872d3b2f7"}, "CenterRight", "2022-12-04 01:19:11", "expressandstar.com", 121175], ["xi jinping", "iran", "joe biden", {"$oid": "64d8f27a516b26587219f904"}, "Left", "2022-12-18 09:00:01", "Alternet", 56758], ["xavi hernandez", "acerbi", "shaun bradley", {"$oid": "64d8e929516b265872e68f03"}, "FarLeft", "2022-11-23 08:48:11", "Upworthy", 26357], ["xavi hernandez", "none", "shaun bradley", {"$oid": "64d8e92a516b265872e69e36"}, "FarLeft", "2022-11-24 13:58:03", "Upworthy", 26357], ["xavi hernandez", "none", "none", {"$oid": "64d8e929516b265872e69098"}, "FarLeft", "2022-11-23 11:22:13", "Upworthy", 26357], ["xavi hernandez", "none", "none", {"$oid": "64d8e92a516b265872e6a4f4"}, "FarLeft", "2022-11-25 09:48:11", "Upworthy", 26357], ["xi jinping", "none", "none", {"$oid": "64d8eac8516b2658721b3e25"}, "CenterRight", "2022-10-31 12:11:00", "liberoquotidiano.it", 308994], ["xi jinping", "none", "none", {"$oid": "64d8eaf5516b265872207e59"}, "CenterRight", "2022-09-20 03:21:00", "liberoquotidiano.it", 308994], ["xi jinping", "vladimir putin", "ukraine", {"$oid": "64d8eb3c516b265872297a2e"}, "FarLeft", "2022-09-15 07:30:00", "Upworthy", 26357], ["xu guilin", "influencers and social media platforms", "seven tourists", {"$oid": "64d8eb19516b26587225009f"}, "FarRight", "2022-08-20 06:30:36", "drudgereport", 1145], ["xavier becerra", "paul flanagan", "sailors and marines", {"$oid": "64d8ea11516b265872042fe7"}, "Right", "2022-08-18 21:16:00", "marinecorpstimes.com", 69162], ["ximena p\u00e1ez", "government of chile", "office of emergency management in los lagos region", {"$oid": "64d8f295516b2658721d4751"}, "CenterRight", "2022-08-03 09:55:06", "biobiochile.cl", 111577], ["xavier becerra", "james wesley hendrix", "b. lynn winmill", {"$oid": "64d8f1af516b265872ff3a33"}, "FarLeft", "2022-08-25 14:57:48", "Talking Points Memo", 113], ["xavier becerra", "state bans", "women", {"$oid": "64d8ee0d516b26587286f062"}, "Right", "2022-07-12 10:06:11", "investmentwatchblog.com", 22294], ["xiomara castro", "daniel ortega", "opposition parties in nicaragua", {"$oid": "64d8f1ee516b265872078f3f"}, "FarLeft", "2022-07-05 14:38:40", "Latino Rebels | Humor, commentary, and analysis. Engaging traviesos.", 104553], ["xi jinping", "donald trump", "china", {"$oid": "64d8ea4f516b2658720c2ac2"}, "FarRight", "2022-05-26 19:00:00", "New American", 21760], ["xuefeng yu", "none", "none", {"$oid": "64d8ea28516b265872072d6d"}, "CenterLeft", "2022-01-15 00:00:00", "biospace.com", 236825], ["xi jinping", "zhong nanshan", "217 people in china", {"$oid": "64d8f1cf516b26587203726c"}, "CenterLeft", "2022-03-15 00:00:00", "fishing-co", 40653], ["xiomara castro", "juan orlando hernandez", "nasry asfura", {"$oid": "64d8ea56516b2658720d09de"}, "Right", "2021-12-01 01:50:00", "newdelhitimes.com", 282902], ["xi jinping", "none", "none", {"$oid": "64d8e996516b265872f464a4"}, "Left", "2021-12-01 01:20:16", "thisisinsider.com", 287512], ["xavi hernandez", "joan laporta", "barcelona", {"$oid": "64d8ed64516b26587271f802"}, "Center", "2021-12-09 13:16:25", "themirror", 40876], ["xi jinping", "politburo", "jiang zemin", {"$oid": "64d8ec5c516b2658724edb42"}, "Right", "2021-11-07 10:53:07", "New York Sun", 28464], ["xiomara castro", "juan orlando hern\u00e1ndez", "berta c\u00e1ceres", {"$oid": "64d8ed33516b2658726b86e9"}, "FarLeft", "2021-12-12 05:57:20", "Jacobin", 26811], ["xiomara castro", "juan orlando hernandez", "honduran citizens", {"$oid": "64d8f12b516b265872ed7142"}, "FarLeft", "2021-11-26 16:24:25", "Democratic Underground", 312], ["xi jinping", "opponents of xi jinping", "shanghai clique", {"$oid": "64d8ef66516b265872b323df"}, "FarRight", "2021-11-07 10:53:07", "New York Sun", 28464], ["xiao zhen xie", "steven jenkins", "xiao zhen xie", {"$oid": "64d8f2fe516b2658722bcbc7"}, "CenterLeft", "2021-11-15 00:00:00", "NBC News", 25499], ["xi jinping", "india", "north korea", {"$oid": "64d8f0e6516b265872e48e93"}, "CenterLeft", "2017-08-01 02:55:36", "indiatoday.intoday.in", 67799], ["xi jinping", "none", "none", {"$oid": "64d8f236516b265872110f6c"}, "Right", "2017-08-01 02:47:11", "CNS News", 20357], ["xi jinping", "none", "none", {"$oid": "64d8ea35516b26587208e9c3"}, "CenterRight", "2017-07-09 05:21:11", "chinadaily", 41626], ["xi jinping", "none", "none", {"$oid": "64d8ea34516b26587208b835"}, "CenterRight", "2017-07-06 08:18:43", "chinadaily", 41626], ["xiaomi mi max 2", "lara croft run", "shruti dhapola", {"$oid": "64d8ec1b516b265872468426"}, "Center", "2017-07-28 05:17:42", "indianexpress.com", 56899], ["xi jinping", "none", "none", {"$oid": "64d8ec1b516b265872467ccd"}, "Center", "2017-07-01 00:16:58", "china.org.cn", 29353], ["xi jinping", "none", "none", {"$oid": "64d8ec1a516b265872466911"}, "Center", "2017-06-01 03:52:42", "china.org.cn", 29353], ["xavier arosemena", "rafael correa", "guillermo lasso", {"$oid": "64d8ec19516b265872463e6c"}, "Left", "2017-04-02 12:41:17", "sinembargo.mx", 105831], ["xavier alexander", "alab pilipinas", "jeric fortuna", {"$oid": "64d8ec19516b265872463e4c"}, "Left", "2017-04-02 08:06:54", "showbizandstyle.inquirer.net", 66218], ["xiao zhen", "none", "he yun le", {"$oid": "64d8f1b2516b265872ff8e34"}, "CenterRight", "2017-04-01 01:37:00", "republika.co.id", 65569], ["xavier jugel\u00e9", "gunman", "xavier jugel\u00e9", {"$oid": "64d8f1b0516b265872ff5e0c"}, "FarLeft", "2017-04-21 09:12:01", "joemygod.com", 278844], ["xi jinping", "none", "none", {"$oid": "64d8ed38516b2658726c43ac"}, "CenterRight", "2017-03-01 00:29:28", "chinadaily", 41626], ["xi jinping", "tobacco lobby", "chinese citizens", {"$oid": "64d8ed38516b2658726c43a7"}, "CenterRight", "2017-03-01 00:29:28", "chinadaily", 41626], ["xscape", "none", "none", {"$oid": "64d8eeb2516b2658729bb5d1"}, "Left", "2017-03-01 12:45:24", "blackamericaweb.com", 70632], ["xi jinping", "kim jong-un", "north korea", {"$oid": "64d8f1b0516b265872ff644a"}, "FarLeft", "2017-04-30 16:59:38", "rinf.com", 53339], ["xaxnar", "neofascism", "trump supporter", {"$oid": "64d8f1b0516b265872ff64f0"}, "FarLeft", "2017-04-19 10:56:00", "Daily Kos", 115], ["xda developers", "oneplus", "none", {"$oid": "64d8eaca516b2658721b6f2e"}, "Right", "2017-02-01 05:29:33", "betanews", 39325], ["xiaoyun liang", "colorectal cancer", "normal-weight postmenopausal women with poor metabolic health", {"$oid": "64d8eba4516b26587237063b"}, "CenterLeft", "2017-02-01 00:00:00", "EurekAlert! - Space and Planetary Science", 5933], ["xi jinping", "china global television network (cgtn)", "worldtribune staff", {"$oid": "64d8f133516b265872ee7363"}, "Right", "2017-01-01 11:30:17", "World Tribune", 68319], ["xbox game pass", "microsoft", "none", {"$oid": "64d8efd5516b265872c0e599"}, "Left", "2016-12-02 09:17:26", "gamesradar.com", 22583], ["xi jinping", "shen jinlong", "wu shengli", {"$oid": "64d8ea2c516b26587207bd4a"}, "FarRight", "2017-01-20 04:44:19", "Washington Times", 101], ["xavier becerra", "donald trump", "california", {"$oid": "64d8efd5516b265872c0e879"}, "Left", "2016-12-02 17:14:35", "The Fresno Bee ", 67], ["xi jinping", "none", "none", {"$oid": "64d8f2f9516b2658722b1ec5"}, "Center", "2016-12-01 23:10:13", "china.org.cn", 29353], ["xi jinping", "none", "none", {"$oid": "64d8f2f9516b2658722b2ae1"}, "Center", "2016-12-02 08:11:52", "china.org.cn", 29353], ["xi jinping", "none", "none", {"$oid": "64d8f132516b265872ee4a79"}, "CenterLeft", "2016-12-01 03:01:22", "variety.com", 19076], ["xi jinping", "china", "south china sea", {"$oid": "64d8f14f516b265872f20ac3"}, "CenterLeft", "2016-11-01 02:54:13", "straitstimesSG", 38895], ["xiang-dong wang", "lung cancer", "mice", {"$oid": "64d8f14f516b265872f20a85"}, "CenterLeft", "2016-11-01 00:00:00", "EurekAlert! - Space and Planetary Science", 5933], ["xavi hernando", "facebook", "norway", {"$oid": "64d8edf7516b265872844645"}, "Center", "2016-11-01 07:00:04", "zdnet", 39330], ["xavier rhodes", "eli manning", "odell beckham jr.", {"$oid": "64d8eeb4516b2658729be210"}, "CenterRight", "2016-10-04 01:22:59", "www.foxsports.com", 55476], ["xur", "none", "none", {"$oid": "64d8f11f516b265872ebe200"}, "Left", "2016-10-07 07:14:40", "gamesradar.com", 22583], ["x-doria", "none", "none", {"$oid": "64d8f11f516b265872ebe452"}, "Left", "2016-10-07 14:00:00", "Macworld", 5687], ["xavier egoavil", "john derosa", "xavier egoavil", {"$oid": "64d8f0b6516b265872de4717"}, "Center", "2016-10-10 08:00:00", "nj.com", 20120], ["xi jinping", "none", "none", {"$oid": "64d8e932516b265872e7c8b8"}, "CenterRight", "2016-09-05 03:10:29", "Daily Mail", 1747], ["xavi hernandez", "none", "none", {"$oid": "64d8e932516b265872e7afcb"}, "CenterRight", "2016-09-03 01:48:12", "republika.co.id", 65569], ["xi jinping", "victim of trade and investment protectionism", "chaolin zhang", {"$oid": "64d8e932516b265872e7c715"}, "CenterRight", "2016-09-05 01:00:08", "chinadaily", 41626], ["xavier becerra", "national institute of family and life advocates (nifla)", "fake clinics", {"$oid": "64d8f0fa516b265872e7155a"}, "FarLeft", "2016-10-14 15:32:10", "rewire.news", 278164], ["xiaomi", "apple", "samsung", {"$oid": "64d8ea3a516b2658720989d5"}, "CenterLeft", "2016-09-01 05:05:54", "Mashable!", 5527], ["xian franzinger barrett", "rahm emanuel", "chicago public school students", {"$oid": "64d8eb33516b2658722840d2"}, "FarLeft", "2016-09-30 11:06:43", "The Progressive ", 151], ["xi jinping", "none", "none", {"$oid": "64d8f12b516b265872ed67a3"}, "Center", "2016-08-16 05:47:38", "china.org.cn", 29353], ["xavier woods", "none", "none", {"$oid": "64d8f12b516b265872ed5e91"}, "Center", "2016-08-11 22:35:00", "comicbook.com", 142830], ["xi jinping", "none", "none", {"$oid": "64d8f12b516b265872ed678c"}, "Center", "2016-08-16 05:47:38", "china.org.cn", 29353], ["x8024 freight train", "none", "none", {"$oid": "64d8f12b516b265872ed66da"}, "Center", "2016-08-16 05:47:38", "china.org.cn", 29353], ["xi jinping", "none", "none", {"$oid": "64d8eb1f516b26587225bd7b"}, "CenterRight", "2016-07-01 05:42:54", "India | Latest India News | Get Free India.com Email | Live Cricket and Entertainment News at India.Com", 271589], ["xiaomi", "none", "none", {"$oid": "64d8f2f9516b2658722b36d4"}, "CenterLeft", "2016-05-20 00:00:00", "Wired", 4434], ["xavier vanneste", "none", "none", {"$oid": "64d8ea38516b265872093be0"}, "Left", "2016-05-05 14:53:53", "Gazeta.ru", 1728], ["xi jinping", "none", "none", {"$oid": "64d8f2cc516b2658722457d7"}, "CenterRight", "2016-04-01 00:19:02", "chinadaily", 41626], ["xi jinping", "dprk", "korean peninsula", {"$oid": "64d8ea7b516b26587211b6c7"}, "CenterRight", "2016-02-06 02:13:45", "chinadaily", 41626], ["xiaochun li", "none", "none", {"$oid": "64d8f0b8516b265872de8086"}, "Right", "2016-01-02 13:09:23", "Free Republic", 304], ["xi jinping", "corrupt generals", "chinese soldiers", {"$oid": "64d8f0b8516b265872de801f"}, "Right", "2016-01-02 10:00:00", "asianews", 39555], ["xi jinping", "one-child policy", "couples in china", {"$oid": "64d8efcf516b265872c00f45"}, "CenterRight", "2016-01-01 01:13:37", "Capital News", 106918], ["xi jinping", "none", "charlotte and emilie meaud", {"$oid": "64d8efd0516b265872c04a93"}, "CenterRight", "2016-01-07 00:45:12", "chinadaily", 41626], ["xi jinping", "zhou yongkang", "chinese citizens", {"$oid": "64d8eb1f516b26587225bc75"}, "CenterRight", "2016-07-01 05:19:51", "abc", 39848], ["xiaomi", "none", "none", {"$oid": "64d8ec1b516b265872468709"}, "Center", "2016-07-01 02:59:47", "Business Today", 283382], ["xiaomi", "microsoft", "none", {"$oid": "64d8ec19516b26587246512e"}, "CenterLeft", "2016-06-01 06:06:00", "thestar-my", 40537], ["xintong tiandi technology", "apple", "none", {"$oid": "64d8ebc0516b2658723aba27"}, "CenterRight", "2016-05-04 15:54:47", "Wall Street Journal", 1150], ["xanana gusmao", "australia", "east timor", {"$oid": "64d8f2f9516b2658722b3555"}, "CenterLeft", "2016-05-01 09:50:12", "Sydney Morning Herald", 19320], ["xanana gusmao", "australia", "east timor", {"$oid": "64d8f2f9516b2658722b356c"}, "CenterLeft", "2016-05-01 09:48:12", "The Age", 19197], ["xavier campbell", "none", "none", {"$oid": "64d8f2f9516b2658722b3323"}, "CenterLeft", "2016-05-01 02:22:09", "Sydney Morning Herald", 19320], ["xi jinping", "none", "none", {"$oid": "64d8f2cc516b2658722457d6"}, "CenterRight", "2016-04-01 00:19:02", "chinadaily", 41626], ["xl shop and stop", "none", "none", {"$oid": "64d8f283516b2658721b1174"}, "CenterRight", "2016-03-05 15:52:22", "breakingnews-ie", 39488], ["xi jinping", "none", "none", {"$oid": "64d8efcf516b265872c01685"}, "CenterRight", "2016-01-01 23:56:29", "livemint.com", 56177], ["xi jinping", "none", "none", {"$oid": "64d8e9aa516b265872f6f809"}, "Center", "2016-02-04 14:02:09", "dailymirror.lk", 61084], ["ximena ossand\u00f3n", "pi\u00f1era", "none", {"$oid": "64d8f2f5516b2658722a9930"}, "Right", "2019-04-05 07:42:18", "theclinic.cl", 62217], ["xiaomi", "samsung", "none", {"$oid": "64d8f2ec516b2658722949ae"}, "Center", "2019-04-02 17:23:41.460838", "NDTV.com: India, Business, Bollywood, Cricket, Video and Breaking News", 17973], ["xiaomi mi mix 3", "none", "none", {"$oid": "64d8f2ec516b2658722949de"}, "Center", "2019-04-02 17:46:23.678747", "amazon.co.uk", 19812], ["xi jinping", "none", "none", {"$oid": "64d8eeb2516b2658729bafa3"}, "CenterLeft", "2019-03-01 19:00:00", "Economist", 1106], ["xochytl greer", "none", "none", {"$oid": "64d8f1a7516b265872fdf0f4"}, "Right", "2019-03-01 05:00:45", "Fox News", 1092], ["xi jinping", "doping", "chinese athletes who use performance-enhancing drugs", {"$oid": "64d8ec00516b265872430213"}, "Left", "2019-02-01 05:30:05", "showbizandstyle.inquirer.net", 66218], ["xavier becerra", "terrance mercadal and jared robinet", "sequette clark", {"$oid": "64d8e92f516b265872e764a3"}, "FarLeft", "2019-03-06 01:20:06", "Truth Dig", 23014], ["xavier becerra", "donald trump", "united states", {"$oid": "64d8ed3f516b2658726d34e2"}, "CenterLeft", "2019-02-16 00:00:00", "complex.com", 24937], ["xi jinping", "donald trump", "none", {"$oid": "64d8ea00516b26587201e81e"}, "Center", "2019-02-01 02:44:00", "trendnews-az-ru", 39883], ["xuanhe zhao", "none", "none", {"$oid": "64d8ea00516b26587201e6f9"}, "Center", "2019-02-01 02:44:31", "indianexpress.com", 56899], ["xi jinping", "donald trump", "china-us relations", {"$oid": "64d8eb34516b265872287280"}, "CenterRight", "2019-01-01 02:10:47", "Capital News", 106918], ["xavier becerra", "pg&e", "california residents", {"$oid": "64d8e9b7516b265872f8a01c"}, "Left", "2019-01-01 08:00:46", "Grist", 27343], ["xerona duke", "none", "none", {"$oid": "64d8e9b7516b265872f8a178"}, "Left", "2019-01-01 13:10:21", "bellanaija.com", 61750], ["xi jinping", "donald trump", "china-us relations", {"$oid": "64d8e9b7516b265872f89e67"}, "Left", "2019-01-01 00:21:48", "showbizandstyle.inquirer.net", 66218], ["xi jinping", "donald trump", "none", {"$oid": "64d8f1b7516b265872005b2e"}, "FarLeft", "2019-01-01 17:48:33", "rinf.com", 53339], ["xi jinping", "donald trump", "chinese entrepreneurs", {"$oid": "64d8f130516b265872ee1ae8"}, "CenterRight", "2018-11-01 23:42:25", "Daily Mail", 1747], ["xi jinping", "vladimir putin", "target", {"$oid": "64d8efc6516b265872bede09"}, "FarRight", "2018-11-01 03:08:48", "townhall.com", 19763], ["xavier campbell", "none", "none", {"$oid": "64d8ec5c516b2658724eddef"}, "Center", "2018-11-01 00:30:00", "perthnow.com.au", 26636], ["xiaomi", "samsung", "indian mobile phone market", {"$oid": "64d8eba1516b26587236acb2"}, "Right", "2018-11-01 09:33:02", "thehindubusinessline.com", 67989], ["x\u00f3chitl g\u00e1lvez", "dante delgado", "alfaro", {"$oid": "64d8f1cf516b26587203837f"}, "CenterLeft", "2018-10-01 23:32:48", "proceso", 40015], ["xavi hern\u00e1ndez", "none", "none", {"$oid": "64d8e9a6516b265872f67f40"}, "Right", "2018-10-02 14:53:40", "Republica", 622760], ["xi jinping", "vladimir putin", "donald trump", {"$oid": "64d8f1a1516b265872fd0016"}, "FarRight", "2018-10-31 07:50:18", "townhall.com", 19763], ["xi jinping", "vladimir putin", "donald trump", {"$oid": "64d8f19f516b265872fc9303"}, "FarRight", "2018-10-01 16:17:19", "townhall.com", 19763], ["xu yuan", "china's new tax regulations", "china's independent refiners (teapots)", {"$oid": "64d8ea28516b265872072e78"}, "Center", "2018-10-03 10:32:49.790195", "oilprice.com", 82510], ["xavier saliba", "veles", "valletta", {"$oid": "64d8eede516b265872a1558a"}, "Center", "2018-09-01 07:45:34", "MaltaToday", 40311], ["xeng lor", "xavier calliste", "none", {"$oid": "64d8eba1516b26587236a809"}, "Left", "2018-08-01 07:03:09", "wfae.org", 131959], ["xi jinping", "china", "africa", {"$oid": "64d8ed23516b265872692bd3"}, "FarLeft", "2018-09-04 23:26:48", "rinf.com", 53339], ["xi jinping", "vladimir putin", "none", {"$oid": "64d8f0e1516b265872e3d1d1"}, "FarRight", "2018-09-02 13:38:36", "townhall.com", 19763], ["xeneral webster", "xeneral webster", "the victim of the nurse", {"$oid": "64d8ea55516b2658720ce737"}, "FarRight", "2018-08-13 17:05:32", "Breitbart", 19334], ["xeng lor", "xyavier calliste", "xyavier calliste", {"$oid": "64d8f208516b2658720b18f3"}, "CenterLeft", "2018-08-01 00:08:53", "islandpacket.com", 26172], ["xiu xiu", "villain not specified", "women in the world", {"$oid": "64d8ed3a516b2658726c8586"}, "Left", "2018-07-01 01:06:51.323392", "popmatters", 80430], ["xherdan shaqiri", "liverpool", "stoke city", {"$oid": "64d8f054516b265872d1443d"}, "Right", "2018-07-01 16:54:27", "stokesentinel.co.uk", 176457], ["xi jinping", "donald trump", "iran", {"$oid": "64d8ebc1516b2658723ad9e9"}, "FarLeft", "2018-07-29 22:17:38", "opednews.com", 26363], ["xi jinping", "george friedman", "chinese citizens", {"$oid": "64d8ed41516b2658726d75db"}, "FarRight", "2018-07-02 05:03:09", "HeatStreet", 285605], ["xi jinping", "vladimir putin", "target", {"$oid": "64d8f1ea516b265872071d28"}, "FarRight", "2018-06-24 08:32:15", "townhall.com", 19763], ["xi jinping", "vladimir putin", "donald trump", {"$oid": "64d8f1ea516b2658720726d9"}, "FarRight", "2018-06-27 00:19:47", "townhall.com", 19763], ["xi jinping", "donald trump", "bode miller's daughter", {"$oid": "64d8f1e9516b26587206f49f"}, "FarRight", "2018-06-12 14:02:43", "townhall.com", 19763], ["xi jinping", "vladimir putin", "target", {"$oid": "64d8f1ea516b265872071041"}, "FarRight", "2018-06-20 10:24:10", "townhall.com", 19763], ["xi jinping", "vladimir putin", "target", {"$oid": "64d8ef67516b265872b341ed"}, "FarRight", "2018-05-27 05:43:07", "townhall.com", 19763], ["xue jinbo", "wu zili", "xue jinbo", {"$oid": "64d8f0e8516b265872e4bb28"}, "Center", "2018-05-01 02:32:16.753350", "BBC", 1094], ["xi jinping", "vladimir putin", "target", {"$oid": "64d8f100516b265872e7fa6e"}, "Right", "2018-05-01 03:39:24", "townhall.com", 19763], ["xi jinping", "none", "none", {"$oid": "64d8f09f516b265872db4536"}, "Left", "2018-04-10 05:05:08", "WNYC", 265423], ["xi jinping", "none", "none", {"$oid": "64d8f09f516b265872db4491"}, "Left", "2018-04-10 03:22:23", "WNYC", 265423], ["xander bogaerts", "andrew kittredge", "rick porcello", {"$oid": "64d8f09f516b265872db410a"}, "Left", "2018-04-01 00:12:10", "Bangor Daily News", 20320], ["xi jinping", "trump administration", "united states", {"$oid": "64d8f09f516b265872db453b"}, "Left", "2018-04-10 03:22:00", "kunm.org", 146446], ["xi jinping", "none", "none", {"$oid": "64d8e972516b265872ef9e0d"}, "FarLeft", "2018-04-27 04:46:09", "www.counterpunch.org", 121815], ["xoel l\u00f3pez", "none", "none", {"$oid": "64d8f0f4516b265872e64f1c"}, "Center", "2018-03-01 13:43:46", "El Pais", 5869], ["xu zou", "user practice issues", "imaging systems", {"$oid": "64d8f054516b265872d14b0f"}, "Right", "2018-03-01 09:00:50", "betanews", 39325], ["xavier dolan", "none", "jessica chastain", {"$oid": "64d8f263516b26587216dc3b"}, "Left", "2018-02-06 07:00:00", "index", 42135], ["xi jinping", "deng xiaoping", "chinese citizens", {"$oid": "64d8e974516b265872efea13"}, "FarLeft", "2018-03-20 07:14:04", "Jacobin", 26811], ["xi jinping", "capitalist dynamics in china", "environment", {"$oid": "64d8e974516b265872efdc58"}, "FarLeft", "2018-03-04 18:49:24", "newpol.org", 100212], ["xi jinping", "kim jong un", "north korea", {"$oid": "64d8f0bb516b265872dee3c6"}, "FarRight", "2018-03-29 09:05:07", "AEI", 67934], ["xinran ji", "jonathan delcarmen", "xinran ji", {"$oid": "64d8ef6a516b265872b39123"}, "FarRight", "2018-01-31 00:00:00", "townhall.com", 19763], ["xiaomi", "none", "none", {"$oid": "64d8f26e516b265872186dfb"}, "CenterLeft", "2018-01-01 02:09:36", "Live Hindustan : Hindi News- Hindi Samachar, Breaking Hindi News, Hindi Newsheadlines", 271162], ["xi jinping", "central bankers", "global economy", {"$oid": "64d8ed24516b2658726950ec"}, "FarLeft", "2017-12-28 19:56:43", "counterinformation.wordpress.com", 119749], ["xi jinping", "kim jong-un", "none", {"$oid": "64d8f2cf516b26587224cab1"}, "CenterRight", "2017-11-02 04:50:25", "HindustanTimes", 39872], ["xi jinping", "communist party", "none", {"$oid": "64d8f219516b2658720d5c7c"}, "Center", "2017-11-01 15:30:00", "the-star", 41904], ["xnet", "institutions launching non-anonymous mailboxes", "whistleblowers", {"$oid": "64d8e975516b265872effa44"}, "FarLeft", "2017-11-08 03:48:39", "Counter Punch", 63031], ["xbox live gold", "none", "none", {"$oid": "64d8f17e516b265872f80d17"}, "CenterLeft", "2017-10-01 23:38:04", "youm7.com", 63271], ["xavier martin", "none", "none", {"$oid": "64d8ec98516b265872567fde"}, "Right", "2017-10-01 09:10:25", "Washington Times", 101], ["xuefeng liu", "hpv", "cancer patients", {"$oid": "64d8f17f516b265872f81755"}, "CenterLeft", "2017-10-02 00:00:00", "EurekAlert! - Space and Planetary Science", 5933], ["xian franzinger barrett", "donald trump", "undocumented immigrants", {"$oid": "64d8f153516b265872f29a63"}, "FarLeft", "2017-10-04 12:09:58", "The Progressive ", 151], ["xi jinping", "guo boxiong", "xu caiho", {"$oid": "64d8ee52516b2658728fd040"}, "Center", "2017-09-13 08:19:19", "indianexpress.com", 56899], ["xu zhong", "china's property market", "none", {"$oid": "64d8ed36516b2658726c0402"}, "CenterLeft", "2017-09-01 00:51:16", "thestar-my", 40537], ["xiamen", "none", "none", {"$oid": "64d8f1b7516b2658720054f6"}, "Right", "2017-09-01 08:37:00", "Sputnik News", 182162]], "metadata": {"time": 1711451671.9948366, "limit": 175720}}